31_lec/1_regbank.v
//here the active reset plays a imp role thus we are using the for loop for it

module regbank_V1 (rdData1,rdData2,wrData,sr1,sr2,dr,clk,rst);
    input clk,rst;
    input [31:0] wrData;
    input [4:0] sr1,sr2,dr;
    output [31:0] rdData1,rdData2;

    //internal signals
    integer k;
    reg [31:0] regfile[31:0];

    //continuous assignment to rdData the data read from the regfile
    assign rdData1=regfile[sr1];
    assign rdData2=regfile[sr2];

    always @(posedge clk) begin
        if (rst) begin
            for (k=0;k<=31;k=k+1) begin
                regfile[k]<=31'b0;
            end
        end
        else begin
            regfile[dr]<=wrData;
        end
    end
    
endmodule

31_lec/1_regbank_tb.v
`timescale 1ps/1ps
`include "1_regbank.v"

module regbank_v1_tb();
    reg clk,rst;
    reg [31:0]wrData;
    reg [4:0] sr1,sr2,dr;
    wire [31:0] rdData1,rdData2;

    regbank_V1 regbank_instance1 (.clk(clk),.rst(rst),
    .wrData(wrData),.rdData1(rdData1),.rdData2(rdData2),
    .sr1(sr1),.sr2(sr2),.dr(dr));

    initial begin
        $dumpfile("reg.vcd");
        $dumpvars(0,regbank_v1_tb);

        clk<=1'b0;
        rst<=1'b1;
        #50 $finish;

    end

    initial begin
        #11 rst<=1'b0;
        #1 wrData<=32'd10; dr<=32'd9;
        #2 sr1<=32'd9;

        #3 wrData<=32'd19; dr<=32'd8;
        #2 sr1<=32'd0; sr2<=32'd8; 

        #3 wrData<=32'd11; dr<=32'd6;
        #5 wrData<=32'd20; dr<=32'd6;
        #2 sr1<=32'd8; sr2<=32'd6; 

    end



    //for clock
    always #5 clk<=~clk;

endmodule

31_lec/reg.vcd
$date
	Tue Mar 25 18:41:43 2025
$end
$version
	Icarus Verilog
$end
$timescale
	1ps
$end
$scope module regbank_v1_tb $end
$var wire 32 ! rdData2 [31:0] $end
$var wire 32 " rdData1 [31:0] $end
$var reg 1 # clk $end
$var reg 5 $ dr [4:0] $end
$var reg 1 % rst $end
$var reg 5 & sr1 [4:0] $end
$var reg 5 ' sr2 [4:0] $end
$var reg 32 ( wrData [31:0] $end
$scope module regbank_instance1 $end
$var wire 1 # clk $end
$var wire 5 ) dr [4:0] $end
$var wire 32 * rdData1 [31:0] $end
$var wire 32 + rdData2 [31:0] $end
$var wire 1 % rst $end
$var wire 5 , sr1 [4:0] $end
$var wire 5 - sr2 [4:0] $end
$var wire 32 . wrData [31:0] $end
$var integer 32 / k [31:0] $end
$upscope $end
$upscope $end
$enddefinitions $end
$comment Show the parameter values. $end
$dumpall
$end
#0
$dumpvars
bx /
bx .
bx -
bx ,
bx +
bx *
bx )
bx (
bx '
bx &
1%
bx $
0#
bx "
bx !
$end
#5
b100000 /
1#
#10
0#
#11
0%
#12
b1001 $
b1001 )
b1010 (
b1010 .
#14
b0 "
b0 *
b1001 &
b1001 ,
#15
b1010 "
b1010 *
1#
#17
b1000 $
b1000 )
b10011 (
b10011 .
#19
b0 !
b0 +
b1000 '
b1000 -
b0 "
b0 *
b0 &
b0 ,
#20
0#
#22
b110 $
b110 )
b1011 (
b1011 .
#25
1#
#27
b10100 (
b10100 .
#29
b1011 !
b1011 +
b110 '
b110 -
b1000 &
b1000 ,
#30
0#
#35
b10100 !
b10100 +
1#
