33_lec/1_pipeline.v
module pipeline_ex1 (F,A,B,C,D,clk,rst);
    parameter N = 10;
    input clk,rst;
    input [N-1:0] A,B,C,D;
    output [N-1:0] F;

    reg [N-1:0] L12_x1, L12_x2, L12_D, L23_x3, L23_D, L_34_F;

    assign F=L_34_F;

    always @(posedge clk or posedge rst) begin
        if(rst) begin
            L12_x1<={N{1'b0}};
            L12_x2<={N{1'b0}};
            L12_D<={N{1'b0}};

            L23_x3<={N{1'b0}};
            L23_D<={N{1'b0}};

            L_34_F<={N{1'b0}};
        end
        else begin
            L12_x1<=A+B;
            L12_x2<=C-D;
            L12_D<=D;

            L23_x3<=L12_x1+L12_x2;
            L23_D<=L12_D;

            L_34_F<= L23_x3*L23_D;
        end
    end
endmodule

33_lec/1_pipeline_tb.v
`include "1_pipeline.v"

module pipeline_ex1_tb ();
parameter N=10;
reg [N-1:0] A,B,C,D;
reg clk,rst;
wire [N-1:0] F;

pipeline_ex1 pipeline_ex1_instance1 (.*);

initial begin
    $dumpfile("dumping.vcd");
    $dumpvars(0,pipeline_ex1_tb);
    rst<=1;
    clk<=0;
    A<=10'd0; B<=10'd0; C<=10'd0; D<=10'd0;
    #3 rst<=0;
    #297 $finish;
end

initial begin
    #5  A=10'd1; B<=10'd1; C<=10'd1; D<=10'd1;  
    #10  A=10'd5; B<=10'd2; C<=10'd1; D<=10'd1;  
    #10  A=10'd5; B<=10'd3; C<=10'd3; D<=10'd1;  
    #10  A=10'd6; B<=10'd6; C<=10'd6; D<=10'd2;  
    #10  A=10'd2; B<=10'd1; C<=10'd1; D<=10'd1;  
    #10  A=10'd1; B<=10'd0; C<=10'd0; D<=10'd1;  
    #10  A=10'd1; B<=10'd0; C<=10'd0; D<=10'd1;  
    #10  A=10'd1; B<=10'd0; C<=10'd0; D<=10'd1;  
end

initial begin
    repeat(10) begin
        #10 $display("time: %d, a: %d, b: %d, c: %d, d: %d, F: %d ",
        $time, A, B, C, D, F);
    end    
end


always #5 clk<=~clk;

endmodule

33_lec/dumping.vcd
$date
	Thu Mar 27 11:29:03 2025
$end
$version
	Icarus Verilog
$end
$timescale
	1s
$end
$scope module pipeline_ex1_tb $end
$var wire 10 ! F [9:0] $end
$var parameter 32 " N $end
$var reg 10 # A [9:0] $end
$var reg 10 $ B [9:0] $end
$var reg 10 % C [9:0] $end
$var reg 10 & D [9:0] $end
$var reg 1 ' clk $end
$var reg 1 ( rst $end
$scope module pipeline_ex1_instance1 $end
$var wire 10 ) A [9:0] $end
$var wire 10 * B [9:0] $end
$var wire 10 + C [9:0] $end
$var wire 10 , D [9:0] $end
$var wire 10 - F [9:0] $end
$var wire 1 ' clk $end
$var wire 1 ( rst $end
$var parameter 32 . N $end
$var reg 10 / L12_D [9:0] $end
$var reg 10 0 L12_x1 [9:0] $end
$var reg 10 1 L12_x2 [9:0] $end
$var reg 10 2 L23_D [9:0] $end
$var reg 10 3 L23_x3 [9:0] $end
$var reg 10 4 L_34_F [9:0] $end
$upscope $end
$upscope $end
$enddefinitions $end
$comment Show the parameter values. $end
$dumpall
b1010 .
b1010 "
$end
#0
$dumpvars
b0 4
b0 3
b0 2
b0 1
b0 0
b0 /
b0 -
b0 ,
b0 +
b0 *
b0 )
1(
0'
b0 &
b0 %
b0 $
b0 #
b0 !
$end
#3
0(
#5
b1 /
b10 0
1'
b1 &
b1 ,
b1 %
b1 +
b1 $
b1 *
b1 #
b1 )
#10
0'
#15
b1 2
b10 3
b111 0
1'
b10 $
b10 *
b101 #
b101 )
#20
0'
#25
b10 !
b10 -
b10 4
b111 3
b10 1
b1000 0
1'
b11 %
b11 +
b11 $
b11 *
#30
0'
#35
b111 !
b111 -
b111 4
b1010 3
b10 /
b100 1
b1100 0
1'
b10 &
b10 ,
b110 %
b110 +
b110 $
b110 *
b110 #
b110 )
#40
0'
#45
b1010 !
b1010 -
b1010 4
b10 2
b10000 3
b1 /
b0 1
b11 0
1'
b1 &
b1 ,
b1 %
b1 +
b1 $
b1 *
b10 #
b10 )
#50
0'
#55
b100000 !
b100000 -
b100000 4
b1 2
b11 3
b1111111111 1
b1 0
1'
b0 %
b0 +
b0 $
b0 *
b1 #
b1 )
#60
0'
#65
b11 !
b11 -
b11 4
b0 3
1'
#70
0'
#75
b0 !
b0 -
b0 4
1'
